data_go_mcp/msds_chemical_info/__init__.py
data_go_mcp/msds_chemical_info/api_client.py
data_go_mcp/msds_chemical_info/models.py
data_go_mcp/msds_chemical_info/server.py
data_go_mcp_msds_chemical_info-0.1.1.dist-info/METADATA
data_go_mcp_msds_chemical_info-0.1.1.dist-info/WHEEL
data_go_mcp_msds_chemical_info-0.1.1.dist-info/entry_points.txt
data_go_mcp_msds_chemical_info-0.1.1.dist-info/licenses/LICENSE
data_go_mcp_msds_chemical_info-0.1.1.dist-info/RECORD
