Metadata-Version: 2.4
Name: data-go-mcp.msds-chemical-info
Version: 0.1.1
Summary: MCP server for Material Safety Data Sheets from Korea Occupational Safety and Health Agency
Project-URL: Homepage, https://github.com/datago-mcp/data-go-mcp-servers
Project-URL: Repository, https://github.com/datago-mcp/data-go-mcp-servers
Project-URL: Documentation, https://github.com/datago-mcp/data-go-mcp-servers/tree/main/src/msds-chemical-info
Project-URL: Bug Tracker, https://github.com/datago-mcp/data-go-mcp-servers/issues
Project-URL: Changelog, https://github.com/datago-mcp/data-go-mcp-servers/blob/main/src/msds-chemical-info/CHANGELOG.md
Author: Data.go.kr MCP Servers Contributors
License: Apache-2.0
License-File: LICENSE
Keywords: api,data.go.kr,korea,mcp,msds-chemical-info
Classifier: Development Status :: 3 - Alpha
Classifier: Intended Audience :: Developers
Classifier: License :: OSI Approved :: Apache Software License
Classifier: Programming Language :: Python :: 3
Classifier: Programming Language :: Python :: 3.10
Classifier: Programming Language :: Python :: 3.11
Classifier: Programming Language :: Python :: 3.12
Classifier: Programming Language :: Python :: 3.13
Requires-Python: >=3.10
Requires-Dist: httpx>=0.28.1
Requires-Dist: mcp[cli]>=1.13.0
Requires-Dist: pydantic>=2.11.7
Requires-Dist: python-dotenv>=1.1.1
